sexagesimal_calculator/__init__.py
sexagesimal_calculator/arithmetic.py
sexagesimal_calculator/conversion.py
sexagesimal_calculator/core.py
sexagesimal_calculator/exceptions.py
sexagesimal_calculator/explain.py
sexagesimal_calculator/sexagesimal.py
sexagesimal_calculator/utils.py
sexagesimal_calculator-2.0.1.dist-info/licenses/LICENSE
sexagesimal_calculator-2.0.1.dist-info/WHEEL
sexagesimal_calculator-2.0.1.dist-info/entry_points.txt
sexagesimal_calculator-2.0.1.dist-info/METADATA
sexagesimal_calculator-2.0.1.dist-info/RECORD
