Metadata-Version: 2.4
Name: sexagesimal-calculator
Version: 2.0.1
Summary: Performing calculations in Sexagesimal Coordinate System.
Keywords: sexagesimal,calculator,coordinates,coordinate system
Author: Hrushikesh Pawar
Author-email: Hrushikesh Pawar <hrushikesh.vpawar@gmail.com>
License-Expression: MIT
License-File: LICENSE
Classifier: Development Status :: 5 - Production/Stable
Classifier: Intended Audience :: Education
Classifier: Operating System :: OS Independent
Classifier: Programming Language :: Python :: 3
Classifier: Programming Language :: Python :: 3.10
Classifier: Programming Language :: Python :: 3.11
Classifier: Programming Language :: Python :: 3.12
Classifier: Programming Language :: Python :: 3.13
Classifier: Topic :: Scientific/Engineering :: Mathematics
Requires-Dist: rich>=14.1.0
Requires-Dist: sympy>=1.14.0
Maintainer: Hrushikesh Pawar
Maintainer-email: Hrushikesh Pawar <hrushikesh.vpawar@gmail.com>
Requires-Python: >=3.10
Project-URL: Documentation, https://hrushikeshpawar.github.io/Sexagesimal-Calculator/
Project-URL: Homepage, https://github.com/HrushikeshPawar/Sexagesimal-Calculator
Project-URL: Issue Tracker, https://github.com/HrushikeshPawar/Sexagesimal-Calculator/issues
Project-URL: Repository, https://github.com/HrushikeshPawar/Sexagesimal-Calculator
